calaxis_cli/__init__.py
calaxis_cli/auth.py
calaxis_cli/cli.py
calaxis_cli/websocket_client.py
calaxis_cli/deployment/__init__.py
calaxis_cli/deployment/fastapi_executor.py
calaxis_cli/deployment/torchserve_executor.py
calaxis_cli/training/__init__.py
calaxis_cli/training/executor.py
calaxis_cli/utils/__init__.py
calaxis_cli/utils/api_client.py
calaxis_cli/utils/config.py
calaxis_cli/utils/system_check.py
calaxis_cli-1.0.0.dist-info/licenses/LICENSE
calaxis_cli-1.0.0.dist-info/METADATA
calaxis_cli-1.0.0.dist-info/WHEEL
calaxis_cli-1.0.0.dist-info/entry_points.txt
calaxis_cli-1.0.0.dist-info/top_level.txt
calaxis_cli-1.0.0.dist-info/RECORD
