Metadata-Version: 2.4
Name: calaxis-cli
Version: 1.0.0
Summary: Calaxis AI Platform - Local Training & Deployment CLI
Author-email: Calaxis AI <support@calaxis.ai>
Maintainer-email: Calaxis AI <support@calaxis.ai>
License: Apache-2.0
Project-URL: Homepage, https://calaxis.ai
Project-URL: Documentation, https://docs.calaxis.ai/cli
Project-URL: Repository, https://github.com/calaxis/calaxis-cli
Project-URL: Issues, https://github.com/calaxis/calaxis-cli/issues
Keywords: ai,machine-learning,llm,fine-tuning,lora,qlora,deployment,mlx,cuda,pytorch,transformers
Classifier: Development Status :: 4 - Beta
Classifier: Intended Audience :: Developers
Classifier: Intended Audience :: Science/Research
Classifier: License :: OSI Approved :: Apache Software License
Classifier: Operating System :: OS Independent
Classifier: Programming Language :: Python :: 3
Classifier: Programming Language :: Python :: 3.10
Classifier: Programming Language :: Python :: 3.11
Classifier: Programming Language :: Python :: 3.12
Classifier: Topic :: Scientific/Engineering :: Artificial Intelligence
Classifier: Topic :: Software Development :: Libraries :: Python Modules
Requires-Python: >=3.10
License-File: LICENSE
Requires-Dist: psutil>=5.9.0
Requires-Dist: pyyaml>=6.0
Requires-Dist: requests>=2.28.0
Requires-Dist: keyring>=24.0.0
Requires-Dist: websockets>=11.0
Requires-Dist: rich>=13.0.0
Provides-Extra: training
Requires-Dist: torch>=2.1.0; extra == "training"
Requires-Dist: transformers>=4.35.0; extra == "training"
Requires-Dist: datasets>=2.14.0; extra == "training"
Requires-Dist: peft>=0.6.0; extra == "training"
Requires-Dist: accelerate>=0.24.0; extra == "training"
Requires-Dist: bitsandbytes>=0.41.0; extra == "training"
Requires-Dist: trl>=0.7.0; extra == "training"
Provides-Extra: mlx
Requires-Dist: mlx>=0.0.10; extra == "mlx"
Requires-Dist: mlx-lm>=0.0.10; extra == "mlx"
Provides-Extra: cuda
Requires-Dist: torch>=2.1.0; extra == "cuda"
Requires-Dist: xformers>=0.0.23; extra == "cuda"
Provides-Extra: deployment
Requires-Dist: fastapi>=0.104.0; extra == "deployment"
Requires-Dist: uvicorn[standard]>=0.24.0; extra == "deployment"
Requires-Dist: onnxruntime>=1.16.0; extra == "deployment"
Provides-Extra: torchserve
Requires-Dist: torchserve>=0.9.0; extra == "torchserve"
Requires-Dist: torch-model-archiver>=0.9.0; extra == "torchserve"
Provides-Extra: full
Requires-Dist: torch>=2.1.0; extra == "full"
Requires-Dist: transformers>=4.35.0; extra == "full"
Requires-Dist: datasets>=2.14.0; extra == "full"
Requires-Dist: peft>=0.6.0; extra == "full"
Requires-Dist: accelerate>=0.24.0; extra == "full"
Requires-Dist: bitsandbytes>=0.41.0; extra == "full"
Requires-Dist: trl>=0.7.0; extra == "full"
Requires-Dist: fastapi>=0.104.0; extra == "full"
Requires-Dist: uvicorn[standard]>=0.24.0; extra == "full"
Provides-Extra: dev
Requires-Dist: pytest>=7.0.0; extra == "dev"
Requires-Dist: pytest-cov>=4.0.0; extra == "dev"
Requires-Dist: black>=23.0.0; extra == "dev"
Requires-Dist: isort>=5.12.0; extra == "dev"
Requires-Dist: mypy>=1.0.0; extra == "dev"
Dynamic: license-file
